pypi_test_sh/__init__.py
pypi_test_sh-0.1.0.dist-info/METADATA
pypi_test_sh-0.1.0.dist-info/WHEEL
pypi_test_sh-0.1.0.dist-info/entry_points.txt
pypi_test_sh-0.1.0.dist-info/top_level.txt
pypi_test_sh-0.1.0.dist-info/RECORD
