Metadata-Version: 2.4
Name: pypi-test-sh
Version: 0.1.0
Summary: Add your description here
Author-email: Soonwoo Hong <swhong@princeton.edu>
Requires-Python: >=3.9
Requires-Dist: numpy>=2.0.2
Requires-Dist: scipy
